mensajes/__init__.py
mensajes/adios/__init__.py
mensajes/adios/despedidas.py
mensajes/hola/__init__.py
mensajes/hola/saludos.py
mensajes/tests/__init__.py
mensajes/tests/test_hola.py
Mensajes_diegopolc-6.0.dist-info/LICENSE
Mensajes_diegopolc-6.0.dist-info/METADATA
Mensajes_diegopolc-6.0.dist-info/WHEEL
Mensajes_diegopolc-6.0.dist-info/top_level.txt
Mensajes_diegopolc-6.0.dist-info/RECORD
