Metadata-Version: 2.1
Name: Mensajes-diegopolc
Version: 6.0
Summary: Un paquete para saludar y despedir
Home-page: https://www.hektor.dev
Author: Diego Polo Contreras
Author-email: diego.polo93@outlook.com
License-File: LICENSE
Requires-Dist: numpy >=1.23.0
